matching_statistics/MatchingStatistics.py
matching_statistics/__init__.py
tests/__init__.py
tests/test_matching_statistics.py
matching_statistics-0.3.0.dist-info/METADATA
matching_statistics-0.3.0.dist-info/WHEEL
matching_statistics-0.3.0.dist-info/top_level.txt
matching_statistics-0.3.0.dist-info/RECORD
